tornado_file_server/__init__.py
tornado_file_server/get_ip.py
tornado_file_server/python_version.py
tornado_file_server/serving.py
tornado_file_server/tornado_file_server.py
tornado_file_server-1.1.dist-info/LICENSE
tornado_file_server-1.1.dist-info/METADATA
tornado_file_server-1.1.dist-info/WHEEL
tornado_file_server-1.1.dist-info/top_level.txt
tornado_file_server-1.1.dist-info/RECORD
