Metadata-Version: 2.1
Name: tornado-file-server
Version: 1.1
Summary: A tornado-based file server
Home-page: https://github.com/walkoncross/tornado-file-server
Author: Yafei Zhao
Author-email: zhaoyafei0210@gmail.com
License: UNKNOWN
Project-URL: Bug Tracker, https://github.com/walkoncross/tornado-file-server/issues
Platform: UNKNOWN
Classifier: Programming Language :: Python :: 2
Classifier: Programming Language :: Python :: 3
Classifier: License :: OSI Approved :: MIT License
Classifier: Operating System :: OS Independent
Requires-Python: >=2.7
License-File: LICENSE
